runtime_config/__init__.py
runtime_config/converters.py
runtime_config/entities/__init__.py
runtime_config/entities/runtime_setting_server.py
runtime_config/enums/__init__.py
runtime_config/enums/setting_value_type.py
runtime_config/exceptions.py
runtime_config/libs/__init__.py
runtime_config/libs/asyncio_utils.py
runtime_config/runtime_config.py
runtime_config/sources/__init__.py
runtime_config/sources/base.py
runtime_config/sources/config_server.py
runtime_config_py-0.0.8.dist-info/LICENSE
runtime_config_py-0.0.8.dist-info/WHEEL
runtime_config_py-0.0.8.dist-info/METADATA
runtime_config_py-0.0.8.dist-info/RECORD
