Metadata-Version: 2.1
Name: runtime-config-py
Version: 0.0.8
Summary: Library for runtime updating project settings.
Home-page: https://github.com/runtime-config/runtime-config-py
License: MIT
Author: Aleksey Petrunnik
Author-email: petrunnik.a@gmail.com
Maintainer: Aleksey Petrunnik
Maintainer-email: petrunnik.a@gmail.com
Requires-Python: >=3.8,<3.12
Classifier: Development Status :: 4 - Beta
Classifier: Intended Audience :: Developers
Classifier: Intended Audience :: System Administrators
Classifier: License :: OSI Approved :: MIT License
Classifier: Operating System :: OS Independent
Classifier: Programming Language :: Python
Classifier: Programming Language :: Python :: 3
Classifier: Programming Language :: Python :: 3.8
Classifier: Programming Language :: Python :: 3.9
Classifier: Programming Language :: Python :: 3.10
Classifier: Programming Language :: Python :: 3.11
Classifier: Programming Language :: Python :: 3 :: Only
Classifier: Programming Language :: Python :: 3.10
Classifier: Programming Language :: Python :: 3.11
Classifier: Programming Language :: Python :: 3.8
Classifier: Programming Language :: Python :: 3.9
Classifier: Topic :: Software Development
Provides-Extra: aiohttp
Requires-Dist: aiohttp (>=3.8.1,<4.0.0); extra == "aiohttp"
Requires-Dist: pydantic (>=1.5.0,<2.0.0)
Project-URL: Repository, https://github.com/runtime-config/runtime-config-py
